{
  "flow_type": "data_list",
  "flow_name": "esm_ps_tasks_list",
  "data_list_name": "esm_ps_tasks_data_list",
  "status": "released",
  "rows": [
    {
      "id": "esm_ps_2_colors",
      "type": "beginning",
      "block1_type": "all_text",
      "name": "Two Colors",
      "_translations": {
        "name": {},
        "block1_text": {}
      },
      "_translatedFields": {
        "name": {
          "eng": "Two Colors"
        },
        "block1_text": {
          "eng": "Draw small number of lines across an oval or rectangle. Can the result always be colored with 2 colors?"
        }
      },
      "block1_text": "Draw small number of lines across an oval or rectangle. Can the result always be colored with 2 colors?"
    },
    {
      "id": "esm_ps_board_squares",
      "type": "beginning",
      "block1_type": "all_text",
      "name": "Squares on a Board",
      "_translations": {
        "name": {},
        "block1_text": {}
      },
      "_translatedFields": {
        "name": {
          "eng": "Squares on a Board"
        },
        "block1_text": {
          "eng": "How many squares in an nxn chessboard? How many rectangles on an nxm board? What about if diagonals are allowed?"
        }
      },
      "block1_text": "How many squares in an nxn chessboard? How many rectangles on an nxm board? What about if diagonals are allowed?"
    },
    {
      "id": "esm_ps_8_cubes",
      "type": "beginning",
      "block1_type": "all_text",
      "name": "Eight Cubes",
      "_translations": {
        "name": {},
        "block1_text": {}
      },
      "_translatedFields": {
        "name": {
          "eng": "Eight Cubes"
        },
        "block1_text": {
          "eng": "There are 8 cubes of the same size. Two are red, two are blue, two are green, and two are white. How many ways can these 8 cubes be put together to form a larger cube so that the larger cube has every color on its face?"
        }
      },
      "block1_text": "There are 8 cubes of the same size. Two are red, two are blue, two are green, and two are white. How many ways can these 8 cubes be put together to form a larger cube so that the larger cube has every color on its face?"
    },
    {
      "id": "esm_ps_bugs",
      "type": "beginning",
      "block1_type": "all_text",
      "name": "Combining Bugs",
      "_translations": {
        "name": {},
        "block1_text": {}
      },
      "_translatedFields": {
        "name": {
          "eng": "Combining Bugs"
        },
        "block1_text": {
          "eng": "There are beetles, lizards, and worms. The number of worms is more than the combined total of beetles and lizards. There are 12 heads and 26 legs. How many of each one are there? What if we increase the numbers a lot? What if there are lizards, beetles, and spiders?"
        }
      },
      "block1_text": "There are beetles, lizards, and worms. The number of worms is more than the combined total of beetles and lizards. There are 12 heads and 26 legs. How many of each one are there? What if we increase the numbers a lot? What if there are lizards, beetles, and spiders?"
    },
    {
      "id": "esm_ps_leapfrog",
      "type": "beginning",
      "block1_type": "all_text",
      "name": "Leapfrog",
      "_translations": {
        "name": {},
        "block1_text": {}
      },
      "_translatedFields": {
        "name": {
          "eng": "Leapfrog"
        },
        "block1_text": {
          "eng": "There are 11 holes in a row. There are 5 black pegs in the holes at one end and 5 white pegs in holes on the other end and one empty hole in the middle. A peg can only be moved to an empty hole or jump over another peg into an empty hole. Can the white and black pegs swap ends?"
        }
      },
      "block1_text": "There are 11 holes in a row. There are 5 black pegs in the holes at one end and 5 white pegs in holes on the other end and one empty hole in the middle. A peg can only be moved to an empty hole or jump over another peg into an empty hole. Can the white and black pegs swap ends?"
    },
    {
      "id": "esm_ps_heavy_desk",
      "type": "beginning",
      "block1_type": "all_text",
      "name": "A Heavy Desk",
      "_translations": {
        "name": {},
        "block1_text": {}
      },
      "_translatedFields": {
        "name": {
          "eng": "A Heavy Desk"
        },
        "block1_text": {
          "eng": "A very heavy desk can only be moved by rotating it 90 degrees about one of its four corners. Is it possible to move it so that it is exactly next to its old position and still facing in the same direction?"
        }
      },
      "block1_text": "A very heavy desk can only be moved by rotating it 90 degrees about one of its four corners. Is it possible to move it so that it is exactly next to its old position and still facing in the same direction?"
    },
    {
      "id": "esm_ps_adding_to_15",
      "type": "beginning",
      "block1_type": "all_text",
      "name": "Adding to 15",
      "_translations": {
        "name": {},
        "block1_text": {}
      },
      "_translatedFields": {
        "name": {
          "eng": "Adding to 15"
        },
        "block1_text": {
          "eng": "9 pieces of paper with the numbers 1 to 9 are placed on a table. Players take turns taking a piece of paper. The first player to get a sum of 15 using any three of their numbers wins. What is a winning strategy (if there is one)?"
        }
      },
      "block1_text": "9 pieces of paper with the numbers 1 to 9 are placed on a table. Players take turns taking a piece of paper. The first player to get a sum of 15 using any three of their numbers wins. What is a winning strategy (if there is one)?"
    }
  ],
  "_xlsxPath": "EFM_rich_tasks_high_level_sheets.xlsx"
}