{
  "flow_type": "template",
  "flow_name": "esm_resources",
  "status": "released",
  "rows": [
    {
      "type": "display_group",
      "name": "top_of_page",
      "rows": [
        {
          "type": "title",
          "name": "spacer",
          "value": "Resources",
          "_translations": {
            "value": {}
          },
          "_nested_name": "top_of_page.spacer"
        }
      ],
      "_nested_name": "top_of_page"
    },
    {
      "type": "display_group",
      "name": "resource_finder",
      "style_list": [
        "margin-top: 10px"
      ],
      "rows": [
        {
          "type": "button",
          "name": "button_resources_finder",
          "value": "Resource Finder",
          "_translations": {
            "value": {}
          },
          "action_list": [
            {
              "trigger": "click",
              "action_id": "go_to",
              "args": [
                "esm_resources_finder"
              ],
              "_raw": "click | go_to: esm_resources_finder",
              "_cleaned": "click | go_to: esm_resources_finder"
            }
          ],
          "parameter_list": {
            "style": "short",
            "text_align": "center"
          },
          "_nested_name": "resource_finder.button_resources_finder"
        }
      ],
      "_nested_name": "resource_finder"
    },
    {
      "name": "now",
      "value": "@calc(timestamp())",
      "_translations": {
        "value": {}
      },
      "exclude_from_translation": true,
      "type": "set_variable",
      "_nested_name": "now",
      "_dynamicFields": {
        "value": [
          {
            "fullExpression": "@calc(timestamp())",
            "matchedExpression": "@calc(timestamp())",
            "type": "calc",
            "fieldName": "timestamp()"
          }
        ]
      },
      "_dynamicDependencies": {
        "@calc(timestamp())": [
          "value"
        ]
      }
    },
    {
      "name": "click_history_field_name",
      "value": "pows_button_click_history",
      "_translations": {
        "value": {}
      },
      "exclude_from_translation": true,
      "type": "set_variable",
      "_nested_name": "click_history_field_name"
    },
    {
      "name": "button_click_history",
      "value": "@fields.@local.click_history_field_name ;  @local.now",
      "_translations": {
        "value": {}
      },
      "condition": "!!(@fields.@local.click_history_field_name)",
      "exclude_from_translation": true,
      "type": "set_variable",
      "_nested_name": "button_click_history",
      "_dynamicFields": {
        "value": [
          {
            "fullExpression": "@fields.@local.click_history_field_name ;  @local.now",
            "matchedExpression": "@local.click_history_field_name",
            "type": "local",
            "fieldName": "click_history_field_name"
          },
          {
            "fullExpression": "@fields.@local.click_history_field_name ;  @local.now",
            "matchedExpression": "@local.now",
            "type": "local",
            "fieldName": "now"
          }
        ],
        "condition": [
          {
            "fullExpression": "!!(@fields.@local.click_history_field_name)",
            "matchedExpression": "@local.click_history_field_name",
            "type": "local",
            "fieldName": "click_history_field_name"
          }
        ]
      },
      "_dynamicDependencies": {
        "@local.click_history_field_name": [
          "value",
          "condition"
        ],
        "@local.now": [
          "value"
        ]
      }
    },
    {
      "name": "button_click_history",
      "value": "@local.now",
      "_translations": {
        "value": {}
      },
      "condition": "!(@fields.@local.click_history_field_name)",
      "exclude_from_translation": true,
      "type": "set_variable",
      "_nested_name": "button_click_history",
      "_dynamicFields": {
        "value": [
          {
            "fullExpression": "@local.now",
            "matchedExpression": "@local.now",
            "type": "local",
            "fieldName": "now"
          }
        ],
        "condition": [
          {
            "fullExpression": "!(@fields.@local.click_history_field_name)",
            "matchedExpression": "@local.click_history_field_name",
            "type": "local",
            "fieldName": "click_history_field_name"
          }
        ]
      },
      "_dynamicDependencies": {
        "@local.now": [
          "value"
        ],
        "@local.click_history_field_name": [
          "condition"
        ]
      }
    },
    {
      "type": "display_group",
      "name": "dg_pows",
      "rows": [
        {
          "type": "button",
          "name": "button_pows",
          "value": "Puzzles",
          "_translations": {
            "value": {}
          },
          "action_list": [
            {
              "trigger": "click",
              "action_id": "start_tour",
              "args": [
                "efm_pows_tour"
              ],
              "_raw": "click | start_tour: efm_pows_tour",
              "_cleaned": "click | start_tour: efm_pows_tour"
            },
            {
              "trigger": "click",
              "action_id": "set_field",
              "args": [
                "has_accessed_pows",
                true
              ],
              "_raw": "click | set_field: has_accessed_pows: TRUE",
              "_cleaned": "click | set_field: has_accessed_pows: TRUE"
            },
            {
              "trigger": "click",
              "action_id": "set_field",
              "args": [
                "@local.click_history_field_name",
                "@local.button_click_history"
              ],
              "_raw": "click | set_field:@local.click_history_field_name: @local.button_click_history",
              "_cleaned": "click | set_field:@local.click_history_field_name: @local.button_click_history"
            }
          ],
          "condition": "!@fields.has_accessed_pows",
          "parameter_list": {
            "style": "short",
            "text_align": "center"
          },
          "_nested_name": "dg_pows.button_pows",
          "_dynamicFields": {
            "action_list": {
              "2": {
                "args": {
                  "0": [
                    {
                      "fullExpression": "@local.click_history_field_name",
                      "matchedExpression": "@local.click_history_field_name",
                      "type": "local",
                      "fieldName": "click_history_field_name"
                    }
                  ],
                  "1": [
                    {
                      "fullExpression": "@local.button_click_history",
                      "matchedExpression": "@local.button_click_history",
                      "type": "local",
                      "fieldName": "button_click_history"
                    }
                  ]
                },
                "_raw": [
                  {
                    "fullExpression": "click | set_field:@local.click_history_field_name: @local.button_click_history",
                    "matchedExpression": "@local.click_history_field_name",
                    "type": "local",
                    "fieldName": "click_history_field_name"
                  },
                  {
                    "fullExpression": "click | set_field:@local.click_history_field_name: @local.button_click_history",
                    "matchedExpression": "@local.button_click_history",
                    "type": "local",
                    "fieldName": "button_click_history"
                  }
                ],
                "_cleaned": [
                  {
                    "fullExpression": "click | set_field:@local.click_history_field_name: @local.button_click_history",
                    "matchedExpression": "@local.click_history_field_name",
                    "type": "local",
                    "fieldName": "click_history_field_name"
                  },
                  {
                    "fullExpression": "click | set_field:@local.click_history_field_name: @local.button_click_history",
                    "matchedExpression": "@local.button_click_history",
                    "type": "local",
                    "fieldName": "button_click_history"
                  }
                ]
              }
            },
            "condition": [
              {
                "fullExpression": "!@fields.has_accessed_pows",
                "matchedExpression": "!@fields.has_accessed_pows",
                "type": "fields",
                "fieldName": "has_accessed_pows"
              }
            ]
          },
          "_dynamicDependencies": {
            "@local.click_history_field_name": [
              "action_list.2.args.0",
              "action_list.2._raw",
              "action_list.2._cleaned"
            ],
            "@local.button_click_history": [
              "action_list.2.args.1",
              "action_list.2._raw",
              "action_list.2._cleaned"
            ],
            "!@fields.has_accessed_pows": [
              "condition"
            ]
          }
        },
        {
          "type": "button",
          "name": "button_pows",
          "value": "Puzzles",
          "_translations": {
            "value": {}
          },
          "action_list": [
            {
              "trigger": "click",
              "action_id": "go_to",
              "args": [
                "efm_pow_start"
              ],
              "_raw": "click | go_to: efm_pow_start",
              "_cleaned": "click | go_to: efm_pow_start"
            },
            {
              "trigger": "click",
              "action_id": "set_field",
              "args": [
                "@local.click_history_field_name",
                "@local.button_click_history"
              ],
              "_raw": "click | set_field:@local.click_history_field_name: @local.button_click_history",
              "_cleaned": "click | set_field:@local.click_history_field_name: @local.button_click_history"
            }
          ],
          "condition": "@fields.has_accessed_pows",
          "parameter_list": {
            "style": "short",
            "text_align": "center"
          },
          "_nested_name": "dg_pows.button_pows",
          "_dynamicFields": {
            "action_list": {
              "1": {
                "args": {
                  "0": [
                    {
                      "fullExpression": "@local.click_history_field_name",
                      "matchedExpression": "@local.click_history_field_name",
                      "type": "local",
                      "fieldName": "click_history_field_name"
                    }
                  ],
                  "1": [
                    {
                      "fullExpression": "@local.button_click_history",
                      "matchedExpression": "@local.button_click_history",
                      "type": "local",
                      "fieldName": "button_click_history"
                    }
                  ]
                },
                "_raw": [
                  {
                    "fullExpression": "click | set_field:@local.click_history_field_name: @local.button_click_history",
                    "matchedExpression": "@local.click_history_field_name",
                    "type": "local",
                    "fieldName": "click_history_field_name"
                  },
                  {
                    "fullExpression": "click | set_field:@local.click_history_field_name: @local.button_click_history",
                    "matchedExpression": "@local.button_click_history",
                    "type": "local",
                    "fieldName": "button_click_history"
                  }
                ],
                "_cleaned": [
                  {
                    "fullExpression": "click | set_field:@local.click_history_field_name: @local.button_click_history",
                    "matchedExpression": "@local.click_history_field_name",
                    "type": "local",
                    "fieldName": "click_history_field_name"
                  },
                  {
                    "fullExpression": "click | set_field:@local.click_history_field_name: @local.button_click_history",
                    "matchedExpression": "@local.button_click_history",
                    "type": "local",
                    "fieldName": "button_click_history"
                  }
                ]
              }
            },
            "condition": [
              {
                "fullExpression": "@fields.has_accessed_pows",
                "matchedExpression": "@fields.has_accessed_pows",
                "type": "fields",
                "fieldName": "has_accessed_pows"
              }
            ]
          },
          "_dynamicDependencies": {
            "@local.click_history_field_name": [
              "action_list.1.args.0",
              "action_list.1._raw",
              "action_list.1._cleaned"
            ],
            "@local.button_click_history": [
              "action_list.1.args.1",
              "action_list.1._raw",
              "action_list.1._cleaned"
            ],
            "@fields.has_accessed_pows": [
              "condition"
            ]
          }
        }
      ],
      "_nested_name": "dg_pows"
    },
    {
      "name": "now",
      "value": "@calc(timestamp())",
      "_translations": {
        "value": {}
      },
      "exclude_from_translation": true,
      "type": "set_variable",
      "_nested_name": "now",
      "_dynamicFields": {
        "value": [
          {
            "fullExpression": "@calc(timestamp())",
            "matchedExpression": "@calc(timestamp())",
            "type": "calc",
            "fieldName": "timestamp()"
          }
        ]
      },
      "_dynamicDependencies": {
        "@calc(timestamp())": [
          "value"
        ]
      }
    },
    {
      "name": "click_history_field_name",
      "value": "gas_button_click_history",
      "_translations": {
        "value": {}
      },
      "exclude_from_translation": true,
      "type": "set_variable",
      "_nested_name": "click_history_field_name"
    },
    {
      "name": "button_click_history",
      "value": "@fields.@local.click_history_field_name ;  @local.now",
      "_translations": {
        "value": {}
      },
      "condition": "!!(@fields.@local.click_history_field_name)",
      "exclude_from_translation": true,
      "type": "set_variable",
      "_nested_name": "button_click_history",
      "_dynamicFields": {
        "value": [
          {
            "fullExpression": "@fields.@local.click_history_field_name ;  @local.now",
            "matchedExpression": "@local.click_history_field_name",
            "type": "local",
            "fieldName": "click_history_field_name"
          },
          {
            "fullExpression": "@fields.@local.click_history_field_name ;  @local.now",
            "matchedExpression": "@local.now",
            "type": "local",
            "fieldName": "now"
          }
        ],
        "condition": [
          {
            "fullExpression": "!!(@fields.@local.click_history_field_name)",
            "matchedExpression": "@local.click_history_field_name",
            "type": "local",
            "fieldName": "click_history_field_name"
          }
        ]
      },
      "_dynamicDependencies": {
        "@local.click_history_field_name": [
          "value",
          "condition"
        ],
        "@local.now": [
          "value"
        ]
      }
    },
    {
      "name": "button_click_history",
      "value": "@local.now",
      "_translations": {
        "value": {}
      },
      "condition": "!(@fields.@local.click_history_field_name)",
      "exclude_from_translation": true,
      "type": "set_variable",
      "_nested_name": "button_click_history",
      "_dynamicFields": {
        "value": [
          {
            "fullExpression": "@local.now",
            "matchedExpression": "@local.now",
            "type": "local",
            "fieldName": "now"
          }
        ],
        "condition": [
          {
            "fullExpression": "!(@fields.@local.click_history_field_name)",
            "matchedExpression": "@local.click_history_field_name",
            "type": "local",
            "fieldName": "click_history_field_name"
          }
        ]
      },
      "_dynamicDependencies": {
        "@local.now": [
          "value"
        ],
        "@local.click_history_field_name": [
          "condition"
        ]
      }
    },
    {
      "type": "display_group",
      "name": "dg_gas",
      "rows": [
        {
          "type": "button",
          "name": "button_gas",
          "value": "Games",
          "_translations": {
            "value": {}
          },
          "action_list": [
            {
              "trigger": "click",
              "action_id": "start_tour",
              "args": [
                "efm_gas_tour"
              ],
              "_raw": "click | start_tour: efm_gas_tour",
              "_cleaned": "click | start_tour: efm_gas_tour"
            },
            {
              "trigger": "click",
              "action_id": "set_field",
              "args": [
                "has_accessed_gas",
                true
              ],
              "_raw": "click | set_field: has_accessed_gas: TRUE",
              "_cleaned": "click | set_field: has_accessed_gas: TRUE"
            },
            {
              "trigger": "click",
              "action_id": "set_field",
              "args": [
                "@local.click_history_field_name",
                "@local.button_click_history"
              ],
              "_raw": "click | set_field:@local.click_history_field_name: @local.button_click_history",
              "_cleaned": "click | set_field:@local.click_history_field_name: @local.button_click_history"
            }
          ],
          "condition": "!@fields.has_accessed_gas",
          "parameter_list": {
            "style": "short",
            "text_align": "center"
          },
          "_nested_name": "dg_gas.button_gas",
          "_dynamicFields": {
            "action_list": {
              "2": {
                "args": {
                  "0": [
                    {
                      "fullExpression": "@local.click_history_field_name",
                      "matchedExpression": "@local.click_history_field_name",
                      "type": "local",
                      "fieldName": "click_history_field_name"
                    }
                  ],
                  "1": [
                    {
                      "fullExpression": "@local.button_click_history",
                      "matchedExpression": "@local.button_click_history",
                      "type": "local",
                      "fieldName": "button_click_history"
                    }
                  ]
                },
                "_raw": [
                  {
                    "fullExpression": "click | set_field:@local.click_history_field_name: @local.button_click_history",
                    "matchedExpression": "@local.click_history_field_name",
                    "type": "local",
                    "fieldName": "click_history_field_name"
                  },
                  {
                    "fullExpression": "click | set_field:@local.click_history_field_name: @local.button_click_history",
                    "matchedExpression": "@local.button_click_history",
                    "type": "local",
                    "fieldName": "button_click_history"
                  }
                ],
                "_cleaned": [
                  {
                    "fullExpression": "click | set_field:@local.click_history_field_name: @local.button_click_history",
                    "matchedExpression": "@local.click_history_field_name",
                    "type": "local",
                    "fieldName": "click_history_field_name"
                  },
                  {
                    "fullExpression": "click | set_field:@local.click_history_field_name: @local.button_click_history",
                    "matchedExpression": "@local.button_click_history",
                    "type": "local",
                    "fieldName": "button_click_history"
                  }
                ]
              }
            },
            "condition": [
              {
                "fullExpression": "!@fields.has_accessed_gas",
                "matchedExpression": "!@fields.has_accessed_gas",
                "type": "fields",
                "fieldName": "has_accessed_gas"
              }
            ]
          },
          "_dynamicDependencies": {
            "@local.click_history_field_name": [
              "action_list.2.args.0",
              "action_list.2._raw",
              "action_list.2._cleaned"
            ],
            "@local.button_click_history": [
              "action_list.2.args.1",
              "action_list.2._raw",
              "action_list.2._cleaned"
            ],
            "!@fields.has_accessed_gas": [
              "condition"
            ]
          }
        },
        {
          "type": "button",
          "name": "button_gas",
          "value": "Games",
          "_translations": {
            "value": {}
          },
          "action_list": [
            {
              "trigger": "click",
              "action_id": "go_to",
              "args": [
                "efm_ga_start"
              ],
              "_raw": "click | go_to: efm_ga_start",
              "_cleaned": "click | go_to: efm_ga_start"
            },
            {
              "trigger": "click",
              "action_id": "set_field",
              "args": [
                "@local.click_history_field_name",
                "@local.button_click_history"
              ],
              "_raw": "click | set_field:@local.click_history_field_name: @local.button_click_history",
              "_cleaned": "click | set_field:@local.click_history_field_name: @local.button_click_history"
            }
          ],
          "condition": "@fields.has_accessed_gas",
          "parameter_list": {
            "style": "short",
            "text_align": "center"
          },
          "_nested_name": "dg_gas.button_gas",
          "_dynamicFields": {
            "action_list": {
              "1": {
                "args": {
                  "0": [
                    {
                      "fullExpression": "@local.click_history_field_name",
                      "matchedExpression": "@local.click_history_field_name",
                      "type": "local",
                      "fieldName": "click_history_field_name"
                    }
                  ],
                  "1": [
                    {
                      "fullExpression": "@local.button_click_history",
                      "matchedExpression": "@local.button_click_history",
                      "type": "local",
                      "fieldName": "button_click_history"
                    }
                  ]
                },
                "_raw": [
                  {
                    "fullExpression": "click | set_field:@local.click_history_field_name: @local.button_click_history",
                    "matchedExpression": "@local.click_history_field_name",
                    "type": "local",
                    "fieldName": "click_history_field_name"
                  },
                  {
                    "fullExpression": "click | set_field:@local.click_history_field_name: @local.button_click_history",
                    "matchedExpression": "@local.button_click_history",
                    "type": "local",
                    "fieldName": "button_click_history"
                  }
                ],
                "_cleaned": [
                  {
                    "fullExpression": "click | set_field:@local.click_history_field_name: @local.button_click_history",
                    "matchedExpression": "@local.click_history_field_name",
                    "type": "local",
                    "fieldName": "click_history_field_name"
                  },
                  {
                    "fullExpression": "click | set_field:@local.click_history_field_name: @local.button_click_history",
                    "matchedExpression": "@local.button_click_history",
                    "type": "local",
                    "fieldName": "button_click_history"
                  }
                ]
              }
            },
            "condition": [
              {
                "fullExpression": "@fields.has_accessed_gas",
                "matchedExpression": "@fields.has_accessed_gas",
                "type": "fields",
                "fieldName": "has_accessed_gas"
              }
            ]
          },
          "_dynamicDependencies": {
            "@local.click_history_field_name": [
              "action_list.1.args.0",
              "action_list.1._raw",
              "action_list.1._cleaned"
            ],
            "@local.button_click_history": [
              "action_list.1.args.1",
              "action_list.1._raw",
              "action_list.1._cleaned"
            ],
            "@fields.has_accessed_gas": [
              "condition"
            ]
          }
        }
      ],
      "_nested_name": "dg_gas"
    },
    {
      "name": "now",
      "value": "@calc(timestamp())",
      "_translations": {
        "value": {}
      },
      "exclude_from_translation": true,
      "type": "set_variable",
      "_nested_name": "now",
      "_dynamicFields": {
        "value": [
          {
            "fullExpression": "@calc(timestamp())",
            "matchedExpression": "@calc(timestamp())",
            "type": "calc",
            "fieldName": "timestamp()"
          }
        ]
      },
      "_dynamicDependencies": {
        "@calc(timestamp())": [
          "value"
        ]
      }
    },
    {
      "name": "click_history_field_name",
      "value": "storybooks_button_click_history",
      "_translations": {
        "value": {}
      },
      "exclude_from_translation": true,
      "type": "set_variable",
      "_nested_name": "click_history_field_name"
    },
    {
      "name": "button_click_history",
      "value": "@fields.@local.click_history_field_name ;  @local.now",
      "_translations": {
        "value": {}
      },
      "condition": "!!(@fields.@local.click_history_field_name)",
      "exclude_from_translation": true,
      "type": "set_variable",
      "_nested_name": "button_click_history",
      "_dynamicFields": {
        "value": [
          {
            "fullExpression": "@fields.@local.click_history_field_name ;  @local.now",
            "matchedExpression": "@local.click_history_field_name",
            "type": "local",
            "fieldName": "click_history_field_name"
          },
          {
            "fullExpression": "@fields.@local.click_history_field_name ;  @local.now",
            "matchedExpression": "@local.now",
            "type": "local",
            "fieldName": "now"
          }
        ],
        "condition": [
          {
            "fullExpression": "!!(@fields.@local.click_history_field_name)",
            "matchedExpression": "@local.click_history_field_name",
            "type": "local",
            "fieldName": "click_history_field_name"
          }
        ]
      },
      "_dynamicDependencies": {
        "@local.click_history_field_name": [
          "value",
          "condition"
        ],
        "@local.now": [
          "value"
        ]
      }
    },
    {
      "name": "button_click_history",
      "value": "@local.now",
      "_translations": {
        "value": {}
      },
      "condition": "!(@fields.@local.click_history_field_name)",
      "exclude_from_translation": true,
      "type": "set_variable",
      "_nested_name": "button_click_history",
      "_dynamicFields": {
        "value": [
          {
            "fullExpression": "@local.now",
            "matchedExpression": "@local.now",
            "type": "local",
            "fieldName": "now"
          }
        ],
        "condition": [
          {
            "fullExpression": "!(@fields.@local.click_history_field_name)",
            "matchedExpression": "@local.click_history_field_name",
            "type": "local",
            "fieldName": "click_history_field_name"
          }
        ]
      },
      "_dynamicDependencies": {
        "@local.now": [
          "value"
        ],
        "@local.click_history_field_name": [
          "condition"
        ]
      }
    },
    {
      "type": "display_group",
      "name": "dg_storybooks",
      "rows": [
        {
          "type": "button",
          "name": "button_storybooks",
          "value": "Storybooks",
          "_translations": {
            "value": {}
          },
          "action_list": [
            {
              "trigger": "click",
              "action_id": "start_tour",
              "args": [
                "efm_storybooks_tour"
              ],
              "_raw": "click | start_tour: efm_storybooks_tour",
              "_cleaned": "click | start_tour: efm_storybooks_tour"
            },
            {
              "trigger": "click",
              "action_id": "set_field",
              "args": [
                "has_accessed_storybooks",
                true
              ],
              "_raw": "click | set_field: has_accessed_storybooks: TRUE",
              "_cleaned": "click | set_field: has_accessed_storybooks: TRUE"
            },
            {
              "trigger": "click",
              "action_id": "set_field",
              "args": [
                "@local.click_history_field_name",
                "@local.button_click_history"
              ],
              "_raw": "click | set_field:@local.click_history_field_name: @local.button_click_history",
              "_cleaned": "click | set_field:@local.click_history_field_name: @local.button_click_history"
            }
          ],
          "condition": "!@fields.has_accessed_storybooks",
          "parameter_list": {
            "style": "short",
            "text_align": "center"
          },
          "_nested_name": "dg_storybooks.button_storybooks",
          "_dynamicFields": {
            "action_list": {
              "2": {
                "args": {
                  "0": [
                    {
                      "fullExpression": "@local.click_history_field_name",
                      "matchedExpression": "@local.click_history_field_name",
                      "type": "local",
                      "fieldName": "click_history_field_name"
                    }
                  ],
                  "1": [
                    {
                      "fullExpression": "@local.button_click_history",
                      "matchedExpression": "@local.button_click_history",
                      "type": "local",
                      "fieldName": "button_click_history"
                    }
                  ]
                },
                "_raw": [
                  {
                    "fullExpression": "click | set_field:@local.click_history_field_name: @local.button_click_history",
                    "matchedExpression": "@local.click_history_field_name",
                    "type": "local",
                    "fieldName": "click_history_field_name"
                  },
                  {
                    "fullExpression": "click | set_field:@local.click_history_field_name: @local.button_click_history",
                    "matchedExpression": "@local.button_click_history",
                    "type": "local",
                    "fieldName": "button_click_history"
                  }
                ],
                "_cleaned": [
                  {
                    "fullExpression": "click | set_field:@local.click_history_field_name: @local.button_click_history",
                    "matchedExpression": "@local.click_history_field_name",
                    "type": "local",
                    "fieldName": "click_history_field_name"
                  },
                  {
                    "fullExpression": "click | set_field:@local.click_history_field_name: @local.button_click_history",
                    "matchedExpression": "@local.button_click_history",
                    "type": "local",
                    "fieldName": "button_click_history"
                  }
                ]
              }
            },
            "condition": [
              {
                "fullExpression": "!@fields.has_accessed_storybooks",
                "matchedExpression": "!@fields.has_accessed_storybooks",
                "type": "fields",
                "fieldName": "has_accessed_storybooks"
              }
            ]
          },
          "_dynamicDependencies": {
            "@local.click_history_field_name": [
              "action_list.2.args.0",
              "action_list.2._raw",
              "action_list.2._cleaned"
            ],
            "@local.button_click_history": [
              "action_list.2.args.1",
              "action_list.2._raw",
              "action_list.2._cleaned"
            ],
            "!@fields.has_accessed_storybooks": [
              "condition"
            ]
          }
        },
        {
          "type": "button",
          "name": "button_storybooks",
          "value": "Storybooks",
          "_translations": {
            "value": {}
          },
          "action_list": [
            {
              "trigger": "click",
              "action_id": "go_to",
              "args": [
                "efm_storybooks"
              ],
              "_raw": "click | go_to: efm_storybooks",
              "_cleaned": "click | go_to: efm_storybooks"
            },
            {
              "trigger": "click",
              "action_id": "set_field",
              "args": [
                "@local.click_history_field_name",
                "@local.button_click_history"
              ],
              "_raw": "click | set_field:@local.click_history_field_name: @local.button_click_history",
              "_cleaned": "click | set_field:@local.click_history_field_name: @local.button_click_history"
            }
          ],
          "condition": "@fields.has_accessed_storybooks",
          "parameter_list": {
            "style": "short",
            "text_align": "center"
          },
          "_nested_name": "dg_storybooks.button_storybooks",
          "_dynamicFields": {
            "action_list": {
              "1": {
                "args": {
                  "0": [
                    {
                      "fullExpression": "@local.click_history_field_name",
                      "matchedExpression": "@local.click_history_field_name",
                      "type": "local",
                      "fieldName": "click_history_field_name"
                    }
                  ],
                  "1": [
                    {
                      "fullExpression": "@local.button_click_history",
                      "matchedExpression": "@local.button_click_history",
                      "type": "local",
                      "fieldName": "button_click_history"
                    }
                  ]
                },
                "_raw": [
                  {
                    "fullExpression": "click | set_field:@local.click_history_field_name: @local.button_click_history",
                    "matchedExpression": "@local.click_history_field_name",
                    "type": "local",
                    "fieldName": "click_history_field_name"
                  },
                  {
                    "fullExpression": "click | set_field:@local.click_history_field_name: @local.button_click_history",
                    "matchedExpression": "@local.button_click_history",
                    "type": "local",
                    "fieldName": "button_click_history"
                  }
                ],
                "_cleaned": [
                  {
                    "fullExpression": "click | set_field:@local.click_history_field_name: @local.button_click_history",
                    "matchedExpression": "@local.click_history_field_name",
                    "type": "local",
                    "fieldName": "click_history_field_name"
                  },
                  {
                    "fullExpression": "click | set_field:@local.click_history_field_name: @local.button_click_history",
                    "matchedExpression": "@local.button_click_history",
                    "type": "local",
                    "fieldName": "button_click_history"
                  }
                ]
              }
            },
            "condition": [
              {
                "fullExpression": "@fields.has_accessed_storybooks",
                "matchedExpression": "@fields.has_accessed_storybooks",
                "type": "fields",
                "fieldName": "has_accessed_storybooks"
              }
            ]
          },
          "_dynamicDependencies": {
            "@local.click_history_field_name": [
              "action_list.1.args.0",
              "action_list.1._raw",
              "action_list.1._cleaned"
            ],
            "@local.button_click_history": [
              "action_list.1.args.1",
              "action_list.1._raw",
              "action_list.1._cleaned"
            ],
            "@fields.has_accessed_storybooks": [
              "condition"
            ]
          }
        }
      ],
      "_nested_name": "dg_storybooks"
    }
  ],
  "_xlsxPath": "EFM_high_level_sheets.xlsx"
}